promptpy/__init__.py
promptpy/prompt.py
promptpy/py.typed
promptpy/validators.py
promptpy-0.1.0.dist-info/METADATA
promptpy-0.1.0.dist-info/WHEEL
promptpy-0.1.0.dist-info/licenses/LICENSE.txt
promptpy-0.1.0.dist-info/RECORD
