Metadata-Version: 2.4
Name: promptpy
Version: 0.1.0
Summary: A Python command line input and validation library
Project-URL: Repository, https://github.com/fourtreestech/promptpy
Project-URL: Documentation, https://promptpy.readthedocs.io/
Author-email: Neil Martin <neil@fourtrees.tech>
License-Expression: MIT
License-File: LICENSE.txt
Keywords: cli,command line interface,prompt
Classifier: Development Status :: 4 - Beta
Classifier: Environment :: Console
Classifier: Intended Audience :: Developers
Classifier: Natural Language :: English
Classifier: Programming Language :: Python :: 3.9
Classifier: Programming Language :: Python :: 3.10
Classifier: Programming Language :: Python :: 3.11
Classifier: Programming Language :: Python :: 3.12
Classifier: Programming Language :: Python :: 3.13
Classifier: Topic :: Software Development :: Libraries
Classifier: Typing :: Typed
Requires-Python: >=3.9
Requires-Dist: rich>=13.9.4
